pydantic_to_html/__init__.py
pydantic_to_html/html_renderer.py
pydantic_to_html-0.2.0.dist-info/licenses/LICENSE
pydantic_to_html-0.2.0.dist-info/METADATA
pydantic_to_html-0.2.0.dist-info/WHEEL
pydantic_to_html-0.2.0.dist-info/top_level.txt
pydantic_to_html-0.2.0.dist-info/RECORD
