Metadata-Version: 2.4
Name: pydantic-to-html
Version: 0.2.0
Summary: A library to convert Pydantic models to HTML
Author-email: Tom Counsell <contact@yudame.com>
Project-URL: Homepage, https://github.com/yudame/pydantic-to-html
Project-URL: Bug Tracker, https://github.com/yudame/pydantic-to-html/issues
Project-URL: Documentation, https://github.com/yudame/pydantic-to-html#readme
Project-URL: Changelog, https://github.com/yudame/pydantic-to-html/blob/main/CHANGELOG.md
Classifier: Programming Language :: Python :: 3
Classifier: Programming Language :: Python :: 3.11
Classifier: Programming Language :: Python :: 3.12
Classifier: License :: OSI Approved :: MIT License
Classifier: Operating System :: OS Independent
Classifier: Intended Audience :: Developers
Classifier: Topic :: Software Development :: Libraries :: Python Modules
Classifier: Topic :: Text Processing :: Markup :: HTML
Requires-Python: >=3.11
License-File: LICENSE
Requires-Dist: pydantic>=2.0.0
Dynamic: license-file
